{
    "width": 280,
    "row_height": 22,
    "items": [
        {
            "id": "header_company",
            "type": "text",
            "text": "{{FIRMA_ADI}}",
            "x": 0,
            "y": 10,
            "font_size": 15,
            "font_bold": true,
            "text_align": "center",
            "width": 280
        },
        {
            "id": "header_address",
            "type": "text",
            "text": "{{ADRES}}",
            "x": 0,
            "y": 32,
            "font_size": 10,
            "font_bold": false,
            "text_align": "center",
            "width": 280
        },
        {
            "id": "header_phone",
            "type": "text",
            "text": "Tel: {{TELEFON}}",
            "x": 0,
            "y": 48,
            "font_size": 10,
            "font_bold": false,
            "text_align": "center",
            "width": 280
        },
        {
            "id": "sep1",
            "type": "text",
            "text": "========================================================",
            "x": 0,
            "y": 60,
            "font_size": 9,
            "font_bold": false,
            "text_align": "center",
            "width": 280
        },
        {
            "id": "info_date",
            "type": "text",
            "text": "TARİH : {{TARIH}} {{SAAT}}",
            "x": 0,
            "y": 72,
            "font_size": 9,
            "font_bold": true,
            "text_align": "left",
            "width": 280
        },
        {
            "id": "info_no",
            "type": "text",
            "text": "FİŞ NO: {{FIS_NO}}",
            "x": 0,
            "y": 86,
            "font_size": 9,
            "font_bold": true,
            "text_align": "left",
            "width": 280
        },
        {
            "id": "info_customer",
            "type": "text",
            "text": "SAYIN : {{MUSTERI_ADI}}",
            "x": 0,
            "y": 100,
            "font_size": 9,
            "font_bold": true,
            "text_align": "left",
            "width": 280
        },
        {
            "id": "sep2",
            "type": "text",
            "text": "--------------------------------------------------------",
            "x": 0,
            "y": 115,
            "font_size": 9,
            "font_bold": false,
            "text_align": "center",
            "width": 280
        },
        {
            "id": "col_header_prod",
            "type": "text",
            "text": "ÜRÜN ADI",
            "x": 0,
            "y": 128,
            "font_size": 9,
            "font_bold": true,
            "text_align": "left",
            "width": 140
        },
        {
            "id": "col_header_qty",
            "type": "text",
            "text": "MİKTAR",
            "x": 140,
            "y": 128,
            "font_size": 9,
            "font_bold": true,
            "text_align": "center",
            "width": 50
        },
        {
            "id": "col_header_total",
            "type": "text",
            "text": "TUTAR",
            "x": 210,
            "y": 128,
            "font_size": 9,
            "font_bold": true,
            "text_align": "right",
            "width": 70
        },
        {
            "id": "sep3",
            "type": "text",
            "text": "--------------------------------------------------------",
            "x": 0,
            "y": 138,
            "font_size": 9,
            "font_bold": false,
            "text_align": "center",
            "width": 280
        },
        {
            "id": "row_product",
            "is_product_row": true,
            "type": "text",
            "text": "{{URUN_ADI}}",
            "x": 0,
            "y": 150,
            "font_size": 9,
            "font_bold": false,
            "text_align": "left",
            "width": 150
        },
        {
            "id": "row_center",
            "is_product_row": true,
            "type": "text",
            "text": "{{MIKTAR}} x {{FIYAT}}",
            "x": 150,
            "y": 150,
            "font_size": 8,
            "font_bold": false,
            "text_align": "center",
            "width": 70
        },
        {
            "id": "row_total",
            "is_product_row": true,
            "type": "text",
            "text": "{{SATIR_TOPLAM}}",
            "x": 220,
            "y": 150,
            "font_size": 9,
            "font_bold": true,
            "text_align": "right",
            "width": 60
        },
        {
            "id": "footer_sep",
            "is_dynamic_footer": true,
            "type": "text",
            "text": "--------------------------------------------------------",
            "x": 0,
            "y": 10,
            "font_size": 9,
            "font_bold": false,
            "text_align": "center",
            "width": 280
        },
        {
            "id": "footer_total_label",
            "is_dynamic_footer": true,
            "type": "text",
            "text": "GENEL TOPLAM",
            "x": 0,
            "y": 25,
            "font_size": 11,
            "font_bold": true,
            "text_align": "left",
            "width": 140
        },
        {
            "id": "footer_total_val",
            "is_dynamic_footer": true,
            "type": "text",
            "text": "{{GENEL_TOPLAM}} TL",
            "x": 140,
            "y": 25,
            "font_size": 14,
            "font_bold": true,
            "text_align": "right",
            "width": 140
        },
        {
            "id": "footer_payment",
            "is_dynamic_footer": true,
            "type": "text",
            "text": "Ödeme Tipi: {{ODEME_TIPI}}",
            "x": 0,
            "y": 45,
            "font_size": 9,
            "font_bold": false,
            "text_align": "right",
            "width": 280
        },
        {
            "id": "bakiye_sep",
            "is_dynamic_footer": true,
            "type": "text",
            "text": "-   -   -   -   -   -   -   -   -",
            "x": 0,
            "y": 58,
            "font_size": 9,
            "font_bold": false,
            "text_align": "center",
            "width": 280
        },
        {
            "id": "bakiye_eski_label",
            "is_dynamic_footer": true,
            "type": "text",
            "text": "Önceki Bakiye",
            "x": 0,
            "y": 70,
            "font_size": 9,
            "font_bold": false,
            "text_align": "left",
            "width": 140
        },
        {
            "id": "bakiye_eski_val",
            "is_dynamic_footer": true,
            "type": "text",
            "text": "{{ESKI_BAKIYE}}",
            "x": 140,
            "y": 70,
            "font_size": 9,
            "font_bold": false,
            "text_align": "right",
            "width": 140
        },
        {
            "id": "bakiye_yeni_label",
            "is_dynamic_footer": true,
            "type": "text",
            "text": "Güncel Bakiye",
            "x": 0,
            "y": 85,
            "font_size": 9,
            "font_bold": true,
            "text_align": "left",
            "width": 140
        },
        {
            "id": "bakiye_yeni_val",
            "is_dynamic_footer": true,
            "type": "text",
            "text": "{{YENI_BAKIYE}}",
            "x": 140,
            "y": 85,
            "font_size": 9,
            "font_bold": true,
            "text_align": "right",
            "width": 140
        },
        {
            "id": "footer_sep2",
            "is_dynamic_footer": true,
            "type": "text",
            "text": "========================================================",
            "x": 0,
            "y": 100,
            "font_size": 9,
            "font_bold": false,
            "text_align": "center",
            "width": 280
        },
        {
            "id": "footer_thanks",
            "is_dynamic_footer": true,
            "type": "text",
            "text": "TEŞEKKÜR EDER, YİNE BEKLERİZ.",
            "x": 0,
            "y": 115,
            "font_size": 9,
            "font_bold": true,
            "text_align": "center",
            "width": 280
        },
        {
            "id": "footer_info",
            "is_dynamic_footer": true,
            "type": "text",
            "text": "Malî değeri yoktur, bilgi fişidir.",
            "x": 0,
            "y": 130,
            "font_size": 8,
            "font_bold": false,
            "text_align": "center",
            "width": 280
        }
    ]
}